magiccmds
