Metadata-Version: 2.1
Name: magic-commands
Version: 0.0.13.1.post3
Summary: IPython magic commands, now available in pure Python
Home-page: https://github.com/thatbirdguythatuknownot/magic-commands
Author: Crowthebird
Author-email: nohackingofkrowten@gmail.com
License: AGPL-3.0
Download-URL: https://github.com/thatbirdguythatuknownot/magic-commands/archive/refs/tags/v0.0.13.1-3.zip
Platform: UNKNOWN
Classifier: License :: OSI Approved :: GNU Affero General Public License v3
Classifier: Programming Language :: Python :: 3
License-File: LICENSE.txt
